pda/__init__.py
pda/__main__.py
pda/abc.py
pda/activity.py
pda/appinfo.py
pda/asset.py
pda/audit_logs.py
pda/backoff.py
pda/channel.py
pda/client.py
pda/colour.py
pda/components.py
pda/context_managers.py
pda/embeds.py
pda/emoji.py
pda/enums.py
pda/errors.py
pda/file.py
pda/flags.py
pda/gateway.py
pda/guild.py
pda/http.py
pda/integrations.py
pda/interactions.py
pda/invite.py
pda/iterators.py
pda/member.py
pda/mentions.py
pda/message.py
pda/mixins.py
pda/object.py
pda/oggparse.py
pda/opus.py
pda/partial_emoji.py
pda/permissions.py
pda/player.py
pda/raw_models.py
pda/reaction.py
pda/role.py
pda/shard.py
pda/stage_instance.py
pda/state.py
pda/sticker.py
pda/team.py
pda/template.py
pda/threads.py
pda/user.py
pda/utils.py
pda/voice_client.py
pda/widget.py
pda/ext/commands/__init__.py
pda/ext/commands/_types.py
pda/ext/commands/bot.py
pda/ext/commands/cog.py
pda/ext/commands/context.py
pda/ext/commands/converter.py
pda/ext/commands/cooldowns.py
pda/ext/commands/core.py
pda/ext/commands/errors.py
pda/ext/commands/flags.py
pda/ext/commands/help.py
pda/ext/commands/view.py
pda/ext/tasks/__init__.py
pda/types/__init__.py
pda/types/activity.py
pda/types/appinfo.py
pda/types/audit_log.py
pda/types/channel.py
pda/types/components.py
pda/types/embed.py
pda/types/emoji.py
pda/types/gateway.py
pda/types/guild.py
pda/types/integration.py
pda/types/interactions.py
pda/types/invite.py
pda/types/member.py
pda/types/message.py
pda/types/raw_models.py
pda/types/role.py
pda/types/snowflake.py
pda/types/sticker.py
pda/types/team.py
pda/types/template.py
pda/types/threads.py
pda/types/user.py
pda/types/voice.py
pda/types/webhook.py
pda/types/welcome_screen.py
pda/types/widget.py
pda/ui/__init__.py
pda/ui/button.py
pda/ui/item.py
pda/ui/select.py
pda/ui/view.py
pda/webhook/__init__.py
pda/webhook/async_.py
pda/webhook/sync.py
discord_pda-1.0.1a0.dist-info/METADATA
discord_pda-1.0.1a0.dist-info/WHEEL
discord_pda-1.0.1a0.dist-info/top_level.txt
discord_pda-1.0.1a0.dist-info/RECORD
